deployment/__init__.py
deployment/__main__.py
deployment/application.py
deployment/bootstrap.py
deployment/deployment.py
deployment/task.py
gros_deployer-1.0.0.dist-info/LICENSE
gros_deployer-1.0.0.dist-info/METADATA
gros_deployer-1.0.0.dist-info/WHEEL
gros_deployer-1.0.0.dist-info/entry_points.txt
gros_deployer-1.0.0.dist-info/top_level.txt
gros_deployer-1.0.0.dist-info/RECORD
