Metadata-Version: 2.1
Name: gros-deployer
Version: 1.0.0
Summary: Grip on Software deployment interface
Author-email: Leon Helwerda <l.s.helwerda@liacs.leidenuniv.nl>
License: Apache 2.0
Project-URL: Homepage, https://gros.liacs.nl
Project-URL: PyPI, https://pypi.python.org/pypi/gros-deployer
Project-URL: Source Code, https://github.com/grip-on-software/deployer
Project-URL: Issues, https://github.com/grip-on-software/deployer/issues
Project-URL: Pull Requests, https://github.com/grip-on-software/deployer/pulls
Project-URL: CI: GitHub Actions, https://github.com/grip-on-software/deployer/actions
Project-URL: CI: Coveralls, https://coveralls.io/github/grip-on-software/deployer?branch=master
Project-URL: CI: SonarCloud, https://sonarcloud.io/project/overview?id=grip-on-software_deployer
Keywords: deployment-application,quality-gate
Classifier: Development Status :: 5 - Production/Stable
Classifier: Environment :: Web Environment
Classifier: Intended Audience :: Developers
Classifier: Topic :: Internet :: WWW/HTTP :: HTTP Servers
Classifier: License :: OSI Approved :: Apache Software License
Classifier: Operating System :: OS Independent
Classifier: Programming Language :: Python :: 3
Classifier: Programming Language :: Python :: 3.8
Classifier: Programming Language :: Python :: 3.9
Classifier: Programming Language :: Python :: 3.10
Classifier: Programming Language :: Python :: 3.11
Classifier: Programming Language :: Python :: 3.12
Requires-Python: >=3.8
License-File: LICENSE
Requires-Dist: gros-gatherer ==1.0.0
Requires-Dist: gros-server ==1.0.0
Requires-Dist: bigboat ==1.0.1
Requires-Dist: PyYAML ==6.0.1
